pydeltasnow/__init__.py
pydeltasnow/core.py
pydeltasnow/main.py
pydeltasnow/utils.py
pydeltasnow-0.1.0.dist-info/LICENSE.txt
pydeltasnow-0.1.0.dist-info/METADATA
pydeltasnow-0.1.0.dist-info/WHEEL
pydeltasnow-0.1.0.dist-info/top_level.txt
pydeltasnow-0.1.0.dist-info/RECORD
