Metadata-Version: 2.1
Name: pydeltasnow
Version: 0.1.0
Summary: Reimplementation of the delta.snow model by Winkler et al. 2021: Snow water equivalents exclusively from snow depths and their temporal changes.
Home-page: https://github.com/joAschauer/pydeltasnow
Author: Johannes Aschauer
Author-email: johannes.aschauer@slf.ch
License: GPL-2.0-or-later
Project-URL: Documentation, https://pydeltasnow.readthedocs.io/en/stable/
Project-URL: Source, https://github.com/joAschauer/pydeltasnow
Project-URL: Tracker, https://github.com/joAschauer/pydeltasnow/issues
Platform: any
Classifier: Development Status :: 4 - Beta
Classifier: Programming Language :: Python
Classifier: Programming Language :: Python :: 3.7
Classifier: Programming Language :: Python :: 3.8
Classifier: Programming Language :: Python :: 3.9
Classifier: Intended Audience :: Science/Research
Classifier: License :: OSI Approved :: GNU General Public License v2 or later (GPLv2+)
Classifier: Topic :: Scientific/Engineering :: Hydrology
Classifier: Topic :: Scientific/Engineering :: Physics
Requires-Python: >=3.7
License-File: LICENSE.txt
Requires-Dist: pandas (>=1.3)
Requires-Dist: numpy (<1.21,>=1.17)
Requires-Dist: numba (>=0.53.1)
Requires-Dist: importlib-metadata ; python_version < "3.8"
Provides-Extra: testing
Requires-Dist: setuptools ; extra == 'testing'
Requires-Dist: pytest ; extra == 'testing'
Requires-Dist: pytest-cov ; extra == 'testing'
